termux/API.py
termux/Camera.py
termux/Clipboard.py
termux/Media.py
termux/Microphone.py
termux/Notification.py
termux/SMS.py
termux/Scheduler.py
termux/Sensors.py
termux/Share.py
termux/TTS.py
termux/Telephony.py
termux/UI.py
termux/Wake.py
termux/Wifi.py
termux/__init__.py
termux/android.py
termux/scrip.py
termux_api-1.2.5.2.dist-info/LICENSE
termux_api-1.2.5.2.dist-info/METADATA
termux_api-1.2.5.2.dist-info/WHEEL
termux_api-1.2.5.2.dist-info/top_level.txt
termux_api-1.2.5.2.dist-info/RECORD
