Metadata-Version: 2.1
Name: termux-api
Version: 1.2.5.2
Summary: A package for accessing termux-api
Home-page: https://github.com/shajul/termux-api.git
Author: drshajul
Author-email: drshajul@gmail.com
Classifier: Programming Language :: Python :: 3
Classifier: License :: OSI Approved :: MIT License
Classifier: Operating System :: OS Independent
Requires-Python: >=3.7
License-File: LICENSE
